redshift/__init__.py
redshift/__main__.py
redshift/config.py
redshift/pdb.py
redshift/agent/__init__.py
redshift/agent/agent.py
redshift/agent/tools/__init__.py
redshift/agent/tools/generate_answer.py
redshift/agent/tools/move_frame.py
redshift/agent/tools/print_args.py
redshift/agent/tools/print_expression.py
redshift/agent/tools/print_retval.py
redshift/agent/tools/read_file.py
redshift/agent/tools/show_source.py
redshift/shared/is_internal_frame.py
redshift/shared/serializers.py
redshift/shared/truncator.py
redshift_cli-1.0.1.dist-info/METADATA
redshift_cli-1.0.1.dist-info/WHEEL
redshift_cli-1.0.1.dist-info/entry_points.txt
redshift_cli-1.0.1.dist-info/licenses/LICENSE
redshift_cli-1.0.1.dist-info/RECORD
