Metadata-Version: 2.4
Name: redshift-cli
Version: 1.0.1
Summary: A debugger you can talk to
Project-URL: homepage, https://github.com/shobrook/redshift
Project-URL: repository, https://github.com/shobrook/redshift
Author-email: Jonathan Shobrook <shobrookj@gmail.com>
Maintainer-email: Jonathan Shobrook <shobrookj@gmail.com>
License:                                  Apache License
License-File: LICENSE
Classifier: Programming Language :: Python
Requires-Python: >=3.10
Requires-Dist: rich>=14.0.0
Requires-Dist: saplings>=6.2.0
